vibehdf5/__init__.py
vibehdf5/__main__.py
vibehdf5/column_filter_dialog.py
vibehdf5/column_sort_dialog.py
vibehdf5/column_statistics_dialog.py
vibehdf5/column_visibility_dialog.py
vibehdf5/csv_table_model.py
vibehdf5/draggable_plot_list_widget.py
vibehdf5/drop_tree_view.py
vibehdf5/hdf5_tree_model.py
vibehdf5/hdf5_viewer.py
vibehdf5/plot_options_dialog.py
vibehdf5/scaled_image_label.py
vibehdf5/syntax_highlighter.py
vibehdf5/table_copy_mixin.py
vibehdf5/unique_values_dialog.py
vibehdf5/utilities.py
vibehdf5/icons/icon_csv.png
vibehdf5/icons/icon_excel.png
vibehdf5/icons/icon_html.png
vibehdf5/icons/icon_json.png
vibehdf5/icons/icon_latex.png
vibehdf5/icons/icon_markdown.png
vibehdf5/icons/icons.md
vibehdf5-2.3.0.dist-info/METADATA
vibehdf5-2.3.0.dist-info/WHEEL
vibehdf5-2.3.0.dist-info/entry_points.txt
vibehdf5-2.3.0.dist-info/licenses/LICENSE
vibehdf5-2.3.0.dist-info/RECORD
