Metadata-Version: 2.4
Name: vibehdf5
Version: 2.3.0
Summary: A lightweight GUI to browse and interact with HDF5 file structures
Project-URL: Homepage, https://github.com/jacobwilliams/vibehdf5
Project-URL: Repository, https://github.com/jacobwilliams/vibehdf5
Project-URL: Issues, https://github.com/jacobwilliams/vibehdf5/issues
Author: Jacob Williams
License: MIT
License-File: LICENSE
Keywords: archive,browser,gui,hdf5,viewer
Classifier: Development Status :: 4 - Beta
Classifier: Intended Audience :: Developers
Classifier: Intended Audience :: Science/Research
Classifier: License :: OSI Approved :: MIT License
Classifier: Operating System :: OS Independent
Classifier: Programming Language :: Python :: 3
Classifier: Programming Language :: Python :: 3.10
Classifier: Programming Language :: Python :: 3.11
Classifier: Programming Language :: Python :: 3.12
Classifier: Programming Language :: Python :: 3.13
Classifier: Topic :: Scientific/Engineering
Classifier: Topic :: Software Development :: Libraries :: Python Modules
Requires-Python: >=3.10
Requires-Dist: graphviz>=0.21
Requires-Dist: h5py>=3.0.0
Requires-Dist: matplotlib>=3.5.0
Requires-Dist: networkx>=3.4
Requires-Dist: numpy>=1.20.0
Requires-Dist: openpyxl>=3.1.5
Requires-Dist: pandas>=1.3.0
Requires-Dist: pydot>=4.0.1
Requires-Dist: pygraphviz>=1.14
Requires-Dist: pyqtgraph>=0.14.0
Requires-Dist: qtpy>=2.4.3
Requires-Dist: scipy>=1.15.2
Requires-Dist: tabulate>=0.9.0
Provides-Extra: build
Requires-Dist: pyinstaller>=6.0.0; extra == 'build'
Provides-Extra: dev
Requires-Dist: black>=22.0.0; extra == 'dev'
Requires-Dist: mypy>=0.990; extra == 'dev'
Requires-Dist: pytest>=7.0.0; extra == 'dev'
Requires-Dist: ruff>=0.1.0; extra == 'dev'
Provides-Extra: docs
Requires-Dist: pdoc>=16.0.0; extra == 'docs'
